ce_translit/__init__.py
ce_translit/_transliterator.py
ce_translit/data/cyrl_latn_map.json
ce_translit-1.0.1.dist-info/METADATA
ce_translit-1.0.1.dist-info/WHEEL
ce_translit-1.0.1.dist-info/licenses/LICENSE
ce_translit-1.0.1.dist-info/RECORD
