Metadata-Version: 2.4
Name: ce-translit
Version: 1.0.1
Summary: Transliterate Chechen text from Cyrillic to Latin script using the Chechen Latin alphabet
Project-URL: Homepage, https://github.com/chechen-language/ce-translit-py
Project-URL: Repository, https://github.com/chechen-language/ce-translit-py
Project-URL: Issues, https://github.com/chechen-language/ce-translit-py/issues
Author-email: Chechen Language <chechen-language@proton.me>
License-Expression: MIT
License-File: LICENSE
Classifier: Operating System :: OS Independent
Classifier: Programming Language :: Python :: 3
Classifier: Topic :: Text Processing :: Linguistic
Requires-Python: >=3.10
